toolkit_lennart/__init__.py
toolkit_lennart/plot.py
toolkit_lennart/setup.py
toolkit_lennart-0.0.8.dist-info/LICENSE
toolkit_lennart-0.0.8.dist-info/METADATA
toolkit_lennart-0.0.8.dist-info/WHEEL
toolkit_lennart-0.0.8.dist-info/top_level.txt
toolkit_lennart-0.0.8.dist-info/RECORD
