Metadata-Version: 2.1
Name: toolkit-lennart
Version: 0.0.8
Summary: Toolkit for data analysis
Home-page: https://pypi.org/project/toolkit-lennart/0.0.8/
Author: Lennart Rooden
Author-email: Lennart Rooden <lennart.rs@gmail.com>
Classifier: Programming Language :: Python :: 3
Classifier: License :: OSI Approved :: MIT License
Classifier: Operating System :: OS Independent
Requires-Python: >=3.7
License-File: LICENSE
